README.md
setup.cfg
setup.py
dotenv_settings_handler/__init__.py
dotenv_settings_handler/entities.py
dotenv_settings_handler.egg-info/PKG-INFO
dotenv_settings_handler.egg-info/SOURCES.txt
dotenv_settings_handler.egg-info/dependency_links.txt
dotenv_settings_handler.egg-info/requires.txt
dotenv_settings_handler.egg-info/top_level.txt