Metadata-Version: 2.1
Name: dotenv-settings-handler
Version: 0.0.3
Summary: Settings handler to load settings from a DotEnv file or system env variables, using python-dotenv and pydantic.
Home-page: https://github.com/David-Lor/Python-DotEnv-Settings-Handler
Author: David Lorenzo
License: Apache 2.0
Platform: UNKNOWN
Classifier: Development Status :: 3 - Alpha
Classifier: Intended Audience :: Developers
Classifier: License :: OSI Approved :: Apache Software License
Classifier: Programming Language :: Python :: 3
Classifier: Programming Language :: Python :: 3.6
Classifier: Programming Language :: Python :: 3.7
